jata.py
python_jata-1.2.dist-info/LICENSE
python_jata-1.2.dist-info/METADATA
python_jata-1.2.dist-info/WHEEL
python_jata-1.2.dist-info/top_level.txt
python_jata-1.2.dist-info/RECORD
