Metadata-Version: 2.1
Name: python-jata
Version: 1.2
Summary: Typed json data
Home-page: https://gitlab.com/balki/python-jata
Author: balki
Author-email: python-jata@balki.me
License: MPL
Keywords: json,dataclass,REST,typing
Platform: any
Classifier: License :: OSI Approved :: Mozilla Public License 2.0 (MPL 2.0)
Classifier: Programming Language :: Python :: 3
Classifier: Programming Language :: Python :: 3.8
Classifier: Programming Language :: Python :: 3.9
Requires-Python: >=3.8
